ir_datasets_owi/__init__.py
ir_datasets_owi-0.1.1.dist-info/METADATA
ir_datasets_owi-0.1.1.dist-info/WHEEL
ir_datasets_owi-0.1.1.dist-info/RECORD
