Metadata-Version: 2.3
Name: ir-datasets-owi
Version: 0.1.1
Summary: 
Author: Gijs Hendriksen
Author-email: info@gijshendriksen.nl
Requires-Python: >=3.10
Classifier: Programming Language :: Python :: 3
Classifier: Programming Language :: Python :: 3.10
Classifier: Programming Language :: Python :: 3.11
Classifier: Programming Language :: Python :: 3.12
Classifier: Programming Language :: Python :: 3.13
Requires-Dist: duckdb (>=1.4.3,<2.0.0)
Requires-Dist: ir-datasets (>=0.5.11,<0.6.0)
